README.md
setup.cfg
setup.py
cstp/__init__.py
cstp.egg-info/PKG-INFO
cstp.egg-info/SOURCES.txt
cstp.egg-info/dependency_links.txt
cstp.egg-info/top_level.txt
cstp.egg-info/zip-safe
cstp/cpyf/CGlobalExitFlag.py
cstp/cpyf/CQueueThread.py
cstp/cpyf/CSockReadWrite.py
cstp/cpyf/CssException.py
cstp/cpyf/__init__.py
cstp/cpyf/_addpath.py
cstp/cpyf/cstpErrorFuncs.py
cstp/cpyf/cstpFuncs.py
cstp/cpyf/mGlobalConst.py
cstp/cpyf/mP2PLayoutConst.py
cstp/hub/CHubCallbackBasicBase.py
cstp/hub/CHubCallbackP2PLayout.py
cstp/hub/CHubCallbackQueueBase.py
cstp/hub/TCmdStringHub.py
cstp/hub/__init__.py
cstp/hub/_addpath.py
cstp/hub/demoSettingsP2PLayout.py
cstp/peer/TCmdStringSck.py
cstp/peer/TCmdStringSckAcctShare.py
cstp/peer/TCmdStringSckP2PLayout.py
cstp/peer/TPeerFreqGatherInfo.py
cstp/peer/__init__.py
cstp/peer/_addpath.py
cstp/pipe/TCmdPipeClient.py
cstp/pipe/TCmdPipeServer.py
cstp/pipe/TCmdPipeServerTCBQ.py
cstp/pipe/TCmdStringSckP2PLayoutPipe.py
cstp/pipe/__init__.py
cstp/pipe/_addpath.py
cstp/run/RunFuncs.py
cstp/run/RunPipePeerServer.py
cstp/run/__init__.py
cstp/test/_addpath.py
cstp/test/tryTCmdStringSckP2PLayout0.py
cstp/test/tryTCmdStringSckP2PLayout00.py
cstp/test/tryTCmdStringSckP2PLayout1.py
cstp/test/tryTCmdStringSckP2PLayout2.py
cstp/cpyf/CGlobalExitFlag.py
cstp/cpyf/CQueueThread.py
cstp/cpyf/CSockReadWrite.py
cstp/cpyf/CssException.py
cstp/cpyf/__init__.py
cstp/cpyf/_addpath.py
cstp/cpyf/cstpErrorFuncs.py
cstp/cpyf/cstpFuncs.py
cstp/cpyf/mGlobalConst.py
cstp/cpyf/mP2PLayoutConst.py
cstp/hub/CHubCallbackBasicBase.py
cstp/hub/CHubCallbackP2PLayout.py
cstp/hub/CHubCallbackQueueBase.py
cstp/hub/TCmdStringHub.py
cstp/hub/__init__.py
cstp/hub/_addpath.py
cstp/hub/demoSettingsP2PLayout.py
cstp/peer/TCmdStringSck.py
cstp/peer/TCmdStringSckAcctShare.py
cstp/peer/TCmdStringSckP2PLayout.py
cstp/peer/TPeerFreqGatherInfo.py
cstp/peer/__init__.py
cstp/peer/_addpath.py
cstp/pipe/TCmdPipeClient.py
cstp/pipe/TCmdPipeServer.py
cstp/pipe/TCmdPipeServerTCBQ.py
cstp/pipe/TCmdStringSckP2PLayoutPipe.py
cstp/pipe/__init__.py
cstp/pipe/_addpath.py
cstp/run/RunFuncs.py
cstp/run/RunPipePeerServer.py
cstp/run/__init__.py
