Metadata-Version: 1.1
Name: cstp
Version: 0.0.104
Summary: CSTP(Command String List Transfer Protocol) wrote by Weber Juche.
Home-page: https://github.com/Weber-JC/PythonEggs/tree/master/cstp
Author: Weber Juche
Author-email: weber.juche@gmail.com
License: MIT
Keywords: public weberFuncs weber
Platform: UNKNOWN
Classifier: License :: OSI Approved :: MIT License
Classifier: Programming Language :: Python
Classifier: Intended Audience :: Developers
Classifier: Operating System :: OS Independent
